avro_object/__init__.py
avro_object/avro_object.py
avro_object/avro_tools.py
avro_object/teste.py
avro_object_furlan-0.9.1.dist-info/LICENSE
avro_object_furlan-0.9.1.dist-info/METADATA
avro_object_furlan-0.9.1.dist-info/WHEEL
avro_object_furlan-0.9.1.dist-info/top_level.txt
avro_object_furlan-0.9.1.dist-info/RECORD
