Metadata-Version: 2.1
Name: avro-object-furlan
Version: 0.9.1
Summary: Helper class for (de)serialization of objects using Apache Avro
Home-page: https://github.com/guionardo/py_avroobject
Author: Guionardo Furlan
Author-email: guionardo@gmail.com
License: UNKNOWN
Platform: UNKNOWN
Classifier: Programming Language :: Python :: 3
Classifier: License :: OSI Approved :: MIT License
Classifier: Operating System :: OS Independent
Classifier: Development Status :: 4 - Beta
Classifier: Intended Audience :: Developers
Requires-Python: >=3.6
Requires-Dist: fastavro
Requires-Dist: requests
